cachemethod.py
cachemethod-1.0.0.dist-info/METADATA
cachemethod-1.0.0.dist-info/WHEEL
cachemethod-1.0.0.dist-info/RECORD
