Metadata-Version: 2.1
Name: cachemethod
Version: 1.0.0
Summary: 
Author: daniel sonbolian
Author-email: dsal3389@gmail.com
Requires-Python: >=3.10,<4.0
Classifier: Programming Language :: Python :: 3
Classifier: Programming Language :: Python :: 3.10
Classifier: Programming Language :: Python :: 3.11
Classifier: Programming Language :: Python :: 3.12
